[
  {
    "line_number": 14,
    "text": "高分经典",
    "url": "https://www.dytt8.com/html/gndy/jddy/20160320/50541.html"
  },
  {
    "line_number": 15,
    "text": "收藏本站",
    "url": "https://www.dytt8.com"
  },
  {
    "line_number": 16,
    "text": "APP下载",
    "url": "https://www.dytt8.com/app.htm"
  },
  {
    "line_number": 20,
    "text": "IMDB评分8分左右影片400余部",
    "url": "https://www.dytt8.com/html/gndy/jddy/20160320/50541.html"
  },
  {
    "line_number": 20,
    "text": "2024年纪录片《今年二十二》H",
    "url": "https://www.dytt8.com/html/gndy/dyzz/20250331/66075.html"
  },
  {
    "line_number": 20,
    "text": "2024年动作喜剧《刺猬索尼克3",
    "url": "https://www.dytt8.com/html/gndy/dyzz/20250331/66074.html"
  },
  {
    "line_number": 20,
    "text": "2024年剧情动作《误判》BD国",
    "url": "https://www.dytt8.com/html/gndy/dyzz/20250331/66073.html"
  },
  {
    "line_number": 20,
    "text": "2025年喜剧《亚历山大和他最",
    "url": "https://www.dytt8.com/html/gndy/jddy/20250330/66070.html"
  },
  {
    "line_number": 20,
    "text": "2024年奇幻动画《不死者之王",
    "url": "https://www.dytt8.com/html/gndy/dyzz/20250330/66069.html"
  },
  {
    "line_number": 20,
    "text": "2024年动画《蓦然回首》HD国",
    "url": "https://www.dytt8.com/html/gndy/dyzz/20250329/66068.html"
  },
  {
    "line_number": 20,
    "text": "2024年剧情动作灾难《焚城》H",
    "url": "https://www.dytt8.com/html/gndy/dyzz/20250328/66067.html"
  },
  {
    "line_number": 20,
    "text": "2025年惊悚《荷兰镇》BD英语",
    "url": "https://www.dytt8.com/html/gndy/dyzz/20250328/66066.html"
  },
  {
    "line_number": 20,
    "text": "2024年恐怖喜剧《诡才之道/鬼",
    "url": "https://www.dytt8.com/html/gndy/dyzz/20250328/66065.html"
  },
  {
    "line_number": 20,
    "text": "2025年惊悚动作《插翅难飞/高",
    "url": "https://www.dytt8.com/html/gndy/jddy/20250328/66064.html"
  },
  {
    "line_number": 20,
    "text": "2024年惊悚犯罪《寂静时刻》B",
    "url": "https://www.dytt8.com/html/gndy/dyzz/20250327/66063.html"
  },
  {
    "line_number": 20,
    "text": "2025年奇幻喜剧《二龙湖水怪",
    "url": "https://www.dytt8.com/html/gndy/jddy/20250327/66062.html"
  },
  {
    "line_number": 20,
    "text": "2025年惊悚恐怖《密室逃生》H",
    "url": "https://www.dytt8.com/html/gndy/jddy/20250327/66061.html"
  },
  {
    "line_number": 20,
    "text": "2024年剧情冒险《迷路/征服山",
    "url": "https://www.dytt8.com/html/gndy/dyzz/20250326/66059.html"
  },
  {
    "line_number": 20,
    "text": "2025年恐怖《怪猴/嗜血怪猴》",
    "url": "https://www.dytt8.com/html/gndy/dyzz/20250326/66058.html"
  },
  {
    "line_number": 20,
    "text": "2025年犯罪喜剧《乌合之众》B",
    "url": "https://www.dytt8.com/html/gndy/dyzz/20250325/66057.html"
  },
  {
    "line_number": 20,
    "text": "2025年喜剧《BJ单身日记4》BD",
    "url": "https://www.dytt8.com/html/gndy/dyzz/20250325/66056.html"
  },
  {
    "line_number": 20,
    "text": "2025年奇幻喜剧《闺女特烦恼",
    "url": "https://www.dytt8.com/html/gndy/jddy/20250324/66055.html"
  },
  {
    "line_number": 20,
    "text": "2025年科幻喜剧《大画王》HD",
    "url": "https://www.dytt8.com/html/gndy/jddy/20250324/66054.html"
  },
  {
    "line_number": 20,
    "text": "2025年惊悚动作《罪恶清除工",
    "url": "https://www.dytt8.com/html/gndy/jddy/20250324/66053.html"
  },
  {
    "line_number": 20,
    "text": "2024年剧情动作《武替道》BD",
    "url": "https://www.dytt8.com/html/gndy/dyzz/20250323/66051.html"
  },
  {
    "line_number": 20,
    "text": "2025年悬疑惊悚《来自谁的启",
    "url": "https://www.dytt8.com/html/gndy/jddy/20250323/66052.html"
  },
  {
    "line_number": 20,
    "text": "2025年奇幻《西游降魔篇之快",
    "url": "https://www.dytt8.com/html/gndy/jddy/20250322/66047.html"
  },
  {
    "line_number": 20,
    "text": "2025年剧情犯罪《恶行之外》H",
    "url": "https://www.dytt8.com/html/gndy/jddy/20250322/66046.html"
  },
  {
    "line_number": 20,
    "text": "2024年科幻动画《守望者(下)",
    "url": "https://www.dytt8.com/html/gndy/dyzz/20250322/66045.html"
  },
  {
    "line_number": 20,
    "text": "2024年科幻动画《守望者(上)",
    "url": "https://www.dytt8.com/html/gndy/dyzz/20240827/65333.html"
  },
  {
    "line_number": 20,
    "text": "2025年惊悚《最后的呼吸/窒息",
    "url": "https://www.dytt8.com/html/gndy/dyzz/20250321/66044.html"
  },
  {
    "line_number": 20,
    "text": "2024年惊悚《财富流感》BD中",
    "url": "https://www.dytt8.com/html/gndy/dyzz/20250320/66043.html"
  },
  {
    "line_number": 20,
    "text": "2024年动作恐怖《复活之战/尸",
    "url": "https://www.dytt8.com/html/gndy/jddy/20250320/66042.html"
  },
  {
    "line_number": 20,
    "text": "2024年动作悬疑《因果报应/天",
    "url": "https://www.dytt8.com/html/gndy/dyzz/20250320/66041.html"
  },
  {
    "line_number": 20,
    "text": "2025年悬疑恐怖《腥心眼/心眼",
    "url": "https://www.dytt8.com/html/gndy/jddy/20250319/66040.html"
  },
  {
    "line_number": 20,
    "text": "2024年获奖剧情《想象之光》B",
    "url": "https://www.dytt8.com/html/gndy/dyzz/20250319/66039.html"
  },
  {
    "line_number": 20,
    "text": "2023年剧情犯罪《对外秘密：",
    "url": "https://www.dytt8.com/html/gndy/jddy/20250318/66038.html"
  },
  {
    "line_number": 20,
    "text": "2025年科幻动作《恶兽》HD国",
    "url": "https://www.dytt8.com/html/gndy/jddy/20250318/66037.html"
  },
  {
    "line_number": 20,
    "text": "2025年动作喜剧《前任杀神》B",
    "url": "https://www.dytt8.com/html/gndy/jddy/20250318/66036.html"
  },
  {
    "line_number": 20,
    "text": "2025年惊悚恐怖《临界点》BD",
    "url": "https://www.dytt8.com/html/gndy/jddy/20250317/66035.html"
  },
  {
    "line_number": 20,
    "text": "2024年奇幻动画《落凡尘》HD",
    "url": "https://www.dytt8.com/html/gndy/dyzz/20250317/66034.html"
  },
  {
    "line_number": 20,
    "text": "2025年奇幻动作《奇怪的记忆",
    "url": "https://www.dytt8.com/html/gndy/jddy/20250316/66033.html"
  },
  {
    "line_number": 20,
    "text": "2025年动作恐怖《静默地带/丧",
    "url": "https://www.dytt8.com/html/gndy/jddy/20250316/66032.html"
  },
  {
    "line_number": 20,
    "text": "2025年动作科幻《电幻国度》B",
    "url": "https://www.dytt8.com/html/gndy/dyzz/20250316/66031.html"
  },
  {
    "line_number": 20,
    "text": "2025年恐怖《控制狂》BD中英",
    "url": "https://www.dytt8.com/html/gndy/jddy/20250314/66029.html"
  },
  {
    "line_number": 20,
    "text": "2025年动作喜剧《老狗/英雄无",
    "url": "https://www.dytt8.com/html/gndy/jddy/20250314/66028.html"
  },
  {
    "line_number": 20,
    "text": "2024年高分获奖剧情《我仍在",
    "url": "https://www.dytt8.com/html/gndy/dyzz/20250314/66027.html"
  },
  {
    "line_number": 20,
    "text": "2024年《四重星/成为星星的少",
    "url": "https://www.dytt8.com/html/gndy/dyzz/20250314/66026.html"
  },
  {
    "line_number": 20,
    "text": "2024年剧情音乐传记《点金之",
    "url": "https://www.dytt8.com/html/gndy/dyzz/20250313/66025.html"
  },
  {
    "line_number": 20,
    "text": "2025年悬疑动作《赤血营救》H",
    "url": "https://www.dytt8.com/html/gndy/jddy/20250313/66024.html"
  },
  {
    "line_number": 20,
    "text": "2023年剧情科幻《最后的机器",
    "url": "https://www.dytt8.com/html/gndy/jddy/20250313/66023.html"
  },
  {
    "line_number": 20,
    "text": "2023年恐怖《忌怪岛》BD日语",
    "url": "https://www.dytt8.com/html/gndy/jddy/20250312/66022.html"
  },
  {
    "line_number": 20,
    "text": "2024年动画《猫妖小杏》BD日",
    "url": "https://www.dytt8.com/html/gndy/dyzz/20250312/66018.html"
  },
  {
    "line_number": 20,
    "text": "2025年动作《飞速追杀》BD中",
    "url": "https://www.dytt8.com/html/gndy/jddy/20250311/66017.html"
  },
  {
    "line_number": 20,
    "text": "2025年动作战争《虎口夺金》H",
    "url": "https://www.dytt8.com/html/gndy/jddy/20250311/66016.html"
  },
  {
    "line_number": 20,
    "text": "2025年科幻动作《美国队长4》",
    "url": "https://www.dytt8.com/html/gndy/dyzz/20250311/66015.html"
  },
  {
    "line_number": 20,
    "text": "2024年悬疑犯罪《超意神探》B",
    "url": "https://www.dytt8.com/html/gndy/dyzz/20250310/66013.html"
  },
  {
    "line_number": 20,
    "text": "2024年动画《蜡笔小新：我们",
    "url": "https://www.dytt8.com/html/gndy/dyzz/20250310/66012.html"
  },
  {
    "line_number": 20,
    "text": "2024年动画喜剧《海洋奇缘2》",
    "url": "https://www.dytt8.com/html/gndy/dyzz/20250309/66011.html"
  },
  {
    "line_number": 20,
    "text": "2025年动作《九州千秋令》HD",
    "url": "https://www.dytt8.com/html/gndy/jddy/20250308/66009.html"
  },
  {
    "line_number": 20,
    "text": "2024年获奖剧情《五分钱男孩",
    "url": "https://www.dytt8.com/html/gndy/dyzz/20250308/66008.html"
  },
  {
    "line_number": 20,
    "text": "2024年科幻动作《升级/升级换",
    "url": "https://www.dytt8.com/html/gndy/jddy/20250307/66004.html"
  },
  {
    "line_number": 20,
    "text": "2024年悬疑《来聊聊须绪美吧/",
    "url": "https://www.dytt8.com/html/gndy/dyzz/20250307/66003.html"
  },
  {
    "line_number": 20,
    "text": "2025年动作《大漠孤侠》HD国",
    "url": "https://www.dytt8.com/html/gndy/jddy/20250306/66000.html"
  },
  {
    "line_number": 20,
    "text": "2024年奇幻喜剧《帕丁顿熊3：",
    "url": "https://www.dytt8.com/html/gndy/dyzz/20250306/65999.html"
  },
  {
    "line_number": 20,
    "text": "2024年动作喜剧《熊猫计划》B",
    "url": "https://www.dytt8.com/html/gndy/dyzz/20250306/65998.html"
  },
  {
    "line_number": 20,
    "text": "2024年动作战争《十一人的贼",
    "url": "https://www.dytt8.com/html/gndy/dyzz/20250305/65990.html"
  },
  {
    "line_number": 20,
    "text": "2025年动作《36总局：势不两",
    "url": "https://www.dytt8.com/html/gndy/jddy/20250305/65989.html"
  },
  {
    "line_number": 20,
    "text": "2024年动作《归来的玩命警探/",
    "url": "https://www.dytt8.com/html/gndy/jddy/20250304/65987.html"
  },
  {
    "line_number": 20,
    "text": "2023年剧情爱情《再见，我的",
    "url": "https://www.dytt8.com/html/gndy/dyzz/20250304/65986.html"
  },
  {
    "line_number": 20,
    "text": "2025年剧情奇幻《瀚海神龙》H",
    "url": "https://www.dytt8.com/html/gndy/jddy/20250303/65985.html"
  },
  {
    "line_number": 20,
    "text": "2025年战争动作《深山狙击》H",
    "url": "https://www.dytt8.com/html/gndy/jddy/20250303/65984.html"
  },
  {
    "line_number": 20,
    "text": "2024年动作奇幻《传说/神话2",
    "url": "https://www.dytt8.com/html/gndy/dyzz/20250303/65983.html"
  },
  {
    "line_number": 20,
    "text": "2024年动作《角斗士2》BD国英",
    "url": "https://www.dytt8.com/html/gndy/dyzz/20250302/65979.html"
  },
  {
    "line_number": 20,
    "text": "2025年惊悚动作《鬼城杀/恶魔",
    "url": "https://www.dytt8.com/html/gndy/jddy/20250302/65978.html"
  },
  {
    "line_number": 20,
    "text": "2024年悬疑犯罪《杀手们》BD",
    "url": "https://www.dytt8.com/html/gndy/jddy/20250228/65974.html"
  },
  {
    "line_number": 20,
    "text": "2024年剧情喜剧《狂爱》BD中",
    "url": "https://www.dytt8.com/html/gndy/dyzz/20250228/65973.html"
  },
  {
    "line_number": 20,
    "text": "2024年剧情《亲爱的家》BD日",
    "url": "https://www.dytt8.com/html/gndy/dyzz/20250228/65972.html"
  },
  {
    "line_number": 20,
    "text": "2024年动画喜剧《海绵宝宝：",
    "url": "https://www.dytt8.com/html/gndy/dyzz/20250227/65971.html"
  },
  {
    "line_number": 20,
    "text": "2024年剧情音乐传记《无名小",
    "url": "https://www.dytt8.com/html/gndy/dyzz/20250227/65970.html"
  },
  {
    "line_number": 20,
    "text": "2025年动作《生死排爆》HD国",
    "url": "https://www.dytt8.com/html/gndy/jddy/20250226/65969.html"
  },
  {
    "line_number": 20,
    "text": "2024年剧情《破浪男女》BD国",
    "url": "https://www.dytt8.com/html/gndy/jddy/20250226/65968.html"
  },
  {
    "line_number": 20,
    "text": "2024年剧情惊悚《沥青之城/救",
    "url": "https://www.dytt8.com/html/gndy/dyzz/20250226/65967.html"
  },
  {
    "line_number": 20,
    "text": "2025年惊悚恐怖《草迷宫恐怖",
    "url": "https://www.dytt8.com/html/gndy/jddy/20250225/65966.html"
  },
  {
    "line_number": 20,
    "text": "2024年悬疑《隐藏的面孔》BD",
    "url": "https://www.dytt8.com/html/gndy/jddy/20250225/65965.html"
  },
  {
    "line_number": 20,
    "text": "2023年动作惊悚《盲水/鲨人盲",
    "url": "https://www.dytt8.com/html/gndy/jddy/20250224/65962.html"
  },
  {
    "line_number": 20,
    "text": "2024年剧情传记《粗野派/粗犷",
    "url": "https://www.dytt8.com/html/gndy/dyzz/20250224/65961.html"
  },
  {
    "line_number": 20,
    "text": "2024年剧情惊悚《九月五日》B",
    "url": "https://www.dytt8.com/html/gndy/dyzz/20250223/65960.html"
  },
  {
    "line_number": 20,
    "text": "2024年动作喜剧《赤羽骨子的",
    "url": "https://www.dytt8.com/html/gndy/jddy/20250223/65959.html"
  },
  {
    "line_number": 20,
    "text": "2024年剧情喜剧《大都市的爱",
    "url": "https://www.dytt8.com/html/gndy/dyzz/20250223/65954.html"
  },
  {
    "line_number": 20,
    "text": "2024年喜剧《窗前明月，咣！",
    "url": "https://www.dytt8.com/html/gndy/jddy/20250223/65957.html"
  },
  {
    "line_number": 20,
    "text": "2025年玄幻冒险《奇门机关卷",
    "url": "https://www.dytt8.com/html/gndy/jddy/20250223/65956.html"
  },
  {
    "line_number": 20,
    "text": "2025年动作科幻《天马星空》H",
    "url": "https://www.dytt8.com/html/gndy/jddy/20250223/65955.html"
  },
  {
    "line_number": 20,
    "text": "2018年动作惊悚《贼巢/极盗战",
    "url": "https://www.dytt8.com/html/gndy/dyzz/20250221/65951.html"
  },
  {
    "line_number": 20,
    "text": "2025年动作惊悚《贼巢2：绝密",
    "url": "https://www.dytt8.com/html/gndy/dyzz/20250221/65950.html"
  },
  {
    "line_number": 20,
    "text": "2024年剧情爱情《艾曼纽》BD",
    "url": "https://www.dytt8.com/html/gndy/jddy/20250220/65947.html"
  },
  {
    "line_number": 20,
    "text": "2025年动画奇幻《猎魔人：深",
    "url": "https://www.dytt8.com/html/gndy/jddy/20250220/65946.html"
  },
  {
    "line_number": 20,
    "text": "2024年剧情《不想和你有遗憾",
    "url": "https://www.dytt8.com/html/gndy/dyzz/20250219/65945.html"
  },
  {
    "line_number": 20,
    "text": "2024年惊悚恐怖《噬魂岛/深不",
    "url": "https://www.dytt8.com/html/gndy/jddy/20250219/65944.html"
  },
  {
    "line_number": 20,
    "text": "2024年科幻惊悚《完美伴侣》B",
    "url": "https://www.dytt8.com/html/gndy/dyzz/20250219/65943.html"
  },
  {
    "line_number": 20,
    "text": "2024年动画奇幻《狮子王：木",
    "url": "https://www.dytt8.com/html/gndy/dyzz/20250218/65942.html"
  },
  {
    "line_number": 20,
    "text": "2025年动作《特警荣耀》HD国",
    "url": "https://www.dytt8.com/html/gndy/jddy/20250218/65941.html"
  },
  {
    "line_number": 20,
    "text": "2024年剧情《噢，加拿大》BD",
    "url": "https://www.dytt8.com/html/gndy/jddy/20250218/65940.html"
  },
  {
    "line_number": 20,
    "text": "2023年恐怖《害虫/魔蛛巢城/",
    "url": "https://www.dytt8.com/html/gndy/jddy/20250217/65939.html"
  },
  {
    "line_number": 20,
    "text": "2024年高分获奖剧情《神圣无",
    "url": "https://www.dytt8.com/html/gndy/dyzz/20250217/65937.html"
  },
  {
    "line_number": 20,
    "text": "2024年剧情喜剧《真正的痛苦",
    "url": "https://www.dytt8.com/html/gndy/dyzz/20250216/65932.html"
  },
  {
    "line_number": 20,
    "text": "2024年剧情《得宠先生/狗转人",
    "url": "https://www.dytt8.com/html/gndy/dyzz/20250216/65931.html"
  },
  {
    "line_number": 20,
    "text": "2025年动作科幻《峡谷/禁谷》",
    "url": "https://www.dytt8.com/html/gndy/dyzz/20250215/65930.html"
  },
  {
    "line_number": 20,
    "text": "2024年喜剧爱情《“骗骗”喜",
    "url": "https://www.dytt8.com/html/gndy/dyzz/20250214/65929.html"
  },
  {
    "line_number": 20,
    "text": "2025年悬疑《谍徒迷局》HD国",
    "url": "https://www.dytt8.com/html/gndy/jddy/20250214/65928.html"
  },
  {
    "line_number": 20,
    "text": "2024年动作《周末狂飙/台北追",
    "url": "https://www.dytt8.com/html/gndy/jddy/20250214/65927.html"
  },
  {
    "line_number": 20,
    "text": "2025年爱情剧情《青蛇缘起》H",
    "url": "https://www.dytt8.com/html/gndy/jddy/20250213/65925.html"
  },
  {
    "line_number": 20,
    "text": "2025年动作《天虎突击队》HD",
    "url": "https://www.dytt8.com/html/gndy/jddy/20250213/65924.html"
  },
  {
    "line_number": 20,
    "text": "2024年剧情爱情《雨中的情欲",
    "url": "https://www.dytt8.com/html/gndy/jddy/20250213/65923.html"
  },
  {
    "line_number": 20,
    "text": "2025年惊悚悬疑《狐妖传说》H",
    "url": "https://www.dytt8.com/html/gndy/jddy/20250213/65922.html"
  },
  {
    "line_number": 20,
    "text": "2024年剧情喜剧《热辣滚烫》B",
    "url": "https://www.dytt8.com/html/gndy/dyzz/20250213/65921.html"
  },
  {
    "line_number": 20,
    "text": "2024年剧情爱情《听说(韩版)",
    "url": "https://www.dytt8.com/html/gndy/jddy/20250211/65915.html"
  },
  {
    "line_number": 20,
    "text": "2024年恐怖《那个孩子是谁？",
    "url": "https://www.dytt8.com/html/gndy/jddy/20250211/65914.html"
  },
  {
    "line_number": 20,
    "text": "2024年高分获奖纪录片《黑箱",
    "url": "https://www.dytt8.com/html/gndy/dyzz/20250211/65913.html"
  },
  {
    "line_number": 20,
    "text": "2024年动作科幻《幻影战士》B",
    "url": "https://www.dytt8.com/html/gndy/jddy/20250210/65912.html"
  },
  {
    "line_number": 20,
    "text": "2024年恐怖《致命录像带：超",
    "url": "https://www.dytt8.com/html/gndy/dyzz/20250210/65911.html"
  },
  {
    "line_number": 20,
    "text": "2024年剧情《老枪》HD国语中",
    "url": "https://www.dytt8.com/html/gndy/dyzz/20250208/65903.html"
  },
  {
    "line_number": 20,
    "text": "2025年恐怖《狼人/狼男/新狼",
    "url": "https://www.dytt8.com/html/gndy/dyzz/20250208/65902.html"
  },
  {
    "line_number": 20,
    "text": "2024年动画喜剧《十条命》BD",
    "url": "https://www.dytt8.com/html/gndy/dyzz/20250208/65901.html"
  },
  {
    "line_number": 20,
    "text": "2025年惊悚悬疑《阴山异闻录",
    "url": "https://www.dytt8.com/html/gndy/jddy/20250208/65900.html"
  },
  {
    "line_number": 20,
    "text": "2024年剧情《隐藏的真相》HD",
    "url": "https://www.dytt8.com/html/gndy/jddy/20250206/65894.html"
  },
  {
    "line_number": 20,
    "text": "2024年恐怖喜剧《隐形猛禽》B",
    "url": "https://www.dytt8.com/html/gndy/jddy/20250206/65893.html"
  },
  {
    "line_number": 20,
    "text": "2025年奇幻《凤楼传之灵狐传",
    "url": "https://www.dytt8.com/html/gndy/jddy/20250205/65892.html"
  },
  {
    "line_number": 20,
    "text": "2024年剧情《波哥大：最后的",
    "url": "https://www.dytt8.com/html/gndy/jddy/20250205/65891.html"
  },
  {
    "line_number": 20,
    "text": "2025年喜剧《大红包2：龙凤呈",
    "url": "https://www.dytt8.com/html/gndy/jddy/20250204/65886.html"
  },
  {
    "line_number": 20,
    "text": "2024年惊悚《秩序信条》BD中",
    "url": "https://www.dytt8.com/html/gndy/jddy/20250204/65885.html"
  },
  {
    "line_number": 20,
    "text": "2024年剧情悬疑《金钱堡垒》H",
    "url": "https://www.dytt8.com/html/gndy/dyzz/20250204/65876.html"
  },
  {
    "line_number": 20,
    "text": "2024年惊悚《真实身份/正体》",
    "url": "https://www.dytt8.com/html/gndy/dyzz/20250204/65875.html"
  },
  {
    "line_number": 20,
    "text": "2025年喜剧《热情邀约》BD英",
    "url": "https://www.dytt8.com/html/gndy/jddy/20250202/65874.html"
  },
  {
    "line_number": 20,
    "text": "2025年喜剧《暴走财神6》HD国",
    "url": "https://www.dytt8.com/html/gndy/jddy/20250202/65873.html"
  },
  {
    "line_number": 20,
    "text": "2024年喜剧动画《海洋奇缘2》",
    "url": "https://www.dytt8.com/html/gndy/dyzz/20250202/65872.html"
  },
  {
    "line_number": 20,
    "text": "2025年喜剧《假爸爸》HD国语",
    "url": "https://www.dytt8.com/html/gndy/dyzz/20250202/65871.html"
  },
  {
    "line_number": 20,
    "text": "2025年动作《无间猎冰》HD国",
    "url": "https://www.dytt8.com/html/gndy/jddy/20250202/65870.html"
  },
  {
    "line_number": 20,
    "text": "2025年动作战争《谍与蝶/一号",
    "url": "https://www.dytt8.com/html/gndy/jddy/20250201/65869.html"
  },
  {
    "line_number": 20,
    "text": "2023年惊悚恐怖《献祭游戏》B",
    "url": "https://www.dytt8.com/html/gndy/jddy/20250131/65865.html"
  },
  {
    "line_number": 20,
    "text": "2025年动作《大奉打更人之世",
    "url": "https://www.dytt8.com/html/gndy/jddy/20250131/65864.html"
  },
  {
    "line_number": 20,
    "text": "2025年动作悬疑《断毒》HD国",
    "url": "https://www.dytt8.com/html/gndy/jddy/20250131/65863.html"
  },
  {
    "line_number": 20,
    "text": "2025年动作悬疑《追龙番外篇",
    "url": "https://www.dytt8.com/html/gndy/jddy/20250131/65862.html"
  },
  {
    "line_number": 20,
    "text": "2024年剧情动作《误判》HD国",
    "url": "https://www.dytt8.com/html/gndy/dyzz/20250131/65861.html"
  },
  {
    "line_number": 20,
    "text": "2024年剧情《寄了一整个春天",
    "url": "https://www.dytt8.com/html/gndy/dyzz/20250131/65860.html"
  },
  {
    "line_number": 20,
    "text": "2024年剧情《小小的我》HD国",
    "url": "https://www.dytt8.com/html/gndy/dyzz/20250130/65859.html"
  },
  {
    "line_number": 20,
    "text": "2024年悬疑惊悚《小心肝儿》B",
    "url": "https://www.dytt8.com/html/gndy/dyzz/20250130/65858.html"
  },
  {
    "line_number": 20,
    "text": "2025年喜剧《火锅艺术家》HD",
    "url": "https://www.dytt8.com/html/gndy/jddy/20250129/65857.html"
  },
  {
    "line_number": 20,
    "text": "2024年剧情历史《王者归来》B",
    "url": "https://www.dytt8.com/html/gndy/dyzz/20250129/65856.html"
  },
  {
    "line_number": 20,
    "text": "2024年动作《维和防暴队》BD",
    "url": "https://www.dytt8.com/html/gndy/dyzz/20250129/65855.html"
  },
  {
    "line_number": 20,
    "text": "2025年喜剧《东北美发天团》H",
    "url": "https://www.dytt8.com/html/gndy/jddy/20250129/65854.html"
  },
  {
    "line_number": 20,
    "text": "2025年武侠动作《笑傲江湖》H",
    "url": "https://www.dytt8.com/html/gndy/dyzz/20250129/65853.html"
  },
  {
    "line_number": 20,
    "text": "2025年科幻动作《星际迷航：3",
    "url": "https://www.dytt8.com/html/gndy/jddy/20250127/65852.html"
  },
  {
    "line_number": 20,
    "text": "2024年动作喜剧《刺猬索尼克3",
    "url": "https://www.dytt8.com/html/gndy/jddy/20250127/65851.html"
  },
  {
    "line_number": 20,
    "text": "2023年恐怖《七月返归》BD国",
    "url": "https://www.dytt8.com/html/gndy/jddy/20250126/65850.html"
  },
  {
    "line_number": 20,
    "text": "2024年奇幻悬疑惊悚《孤海沙",
    "url": "https://www.dytt8.com/html/gndy/jddy/20250126/65849.html"
  },
  {
    "line_number": 20,
    "text": "2025年动作《黑白潜行2》HD国",
    "url": "https://www.dytt8.com/html/gndy/dyzz/20250125/65844.html"
  },
  {
    "line_number": 20,
    "text": "2024年恐怖喜剧《夜母/暗夜犬",
    "url": "https://www.dytt8.com/html/gndy/dyzz/20250125/65843.html"
  },
  {
    "line_number": 20,
    "text": "2025年喜剧《真爱找麻烦！》H",
    "url": "https://www.dytt8.com/html/gndy/jddy/20250125/65842.html"
  },
  {
    "line_number": 20,
    "text": "2025年动作悬疑《秦岭诡事之",
    "url": "https://www.dytt8.com/html/gndy/jddy/20250124/65841.html"
  },
  {
    "line_number": 20,
    "text": "2024年剧情悬疑《孤星计划》H",
    "url": "https://www.dytt8.com/html/gndy/dyzz/20250124/65840.html"
  },
  {
    "line_number": 20,
    "text": "2024年悬疑恐怖《诺斯费拉图",
    "url": "https://www.dytt8.com/html/gndy/dyzz/20250124/65839.html"
  },
  {
    "line_number": 20,
    "text": "2024年汤姆·汉克斯剧情《此",
    "url": "https://www.dytt8.com/html/gndy/dyzz/20250123/65838.html"
  },
  {
    "line_number": 20,
    "text": "2022年获奖剧情《窄路微尘》B",
    "url": "https://www.dytt8.com/html/gndy/dyzz/20250123/65837.html"
  },
  {
    "line_number": 20,
    "text": "2025年武侠《神雕侠侣：问世",
    "url": "https://www.dytt8.com/html/gndy/jddy/20250122/65835.html"
  },
  {
    "line_number": 20,
    "text": "2024年动作惊悚《空中悍将/勇",
    "url": "https://www.dytt8.com/html/gndy/jddy/20250122/65834.html"
  },
  {
    "line_number": 20,
    "text": "2025年剧情战争《要是晴天就",
    "url": "https://www.dytt8.com/html/gndy/dyzz/20250121/65833.html"
  },
  {
    "line_number": 20,
    "text": "2025年喜剧《象牙山车神》HD",
    "url": "https://www.dytt8.com/html/gndy/jddy/20250121/65832.html"
  },
  {
    "line_number": 20,
    "text": "2024年剧情《天龙押运》HD国",
    "url": "https://www.dytt8.com/html/gndy/jddy/20250121/65831.html"
  },
  {
    "line_number": 20,
    "text": "2025年动作《荣耀之谁与争锋",
    "url": "https://www.dytt8.com/html/gndy/jddy/20250120/65830.html"
  },
  {
    "line_number": 20,
    "text": "2025年惊悚悬疑《寻凶》HD国",
    "url": "https://www.dytt8.com/html/gndy/jddy/20250120/65829.html"
  },
  {
    "line_number": 20,
    "text": "2025年武侠动作《黄沙渡刀客",
    "url": "https://www.dytt8.com/html/gndy/jddy/20250119/65825.html"
  },
  {
    "line_number": 20,
    "text": "2025年武侠动作《勾魂剑》HD",
    "url": "https://www.dytt8.com/html/gndy/jddy/20250119/65824.html"
  },
  {
    "line_number": 20,
    "text": "2025年动作喜剧《重返行动》B",
    "url": "https://www.dytt8.com/html/gndy/dyzz/20250119/65823.html"
  },
  {
    "line_number": 20,
    "text": "2024年剧情《势不可挡》BD英",
    "url": "https://www.dytt8.com/html/gndy/dyzz/20250118/65821.html"
  },
  {
    "line_number": 20,
    "text": "2025年科幻动作《重返侏罗纪",
    "url": "https://www.dytt8.com/html/gndy/jddy/20250117/65820.html"
  },
  {
    "line_number": 20,
    "text": "2024年高分剧情《好东西》HD",
    "url": "https://www.dytt8.com/html/gndy/dyzz/20250117/65819.html"
  },
  {
    "line_number": 20,
    "text": "2024年动作《王者天下4/大将",
    "url": "https://www.dytt8.com/html/gndy/dyzz/20250117/65818.html"
  },
  {
    "line_number": 20,
    "text": "2024年剧情《酷儿》BD中英双",
    "url": "https://www.dytt8.com/html/gndy/dyzz/20250116/65817.html"
  },
  {
    "line_number": 20,
    "text": "2025年科幻惊悚《鲨滩》HD国",
    "url": "https://www.dytt8.com/html/gndy/jddy/20250116/65815.html"
  },
  {
    "line_number": 24,
    "text": "2024年纪录片《今年二十二》HD国语中字",
    "url": "https://www.dytt8.com/html/gndy/dyzz/20250331/66075.html"
  },
  {
    "line_number": 26,
    "text": "2024年动作喜剧《刺猬索尼克3》BD国英双语双字",
    "url": "https://www.dytt8.com/html/gndy/dyzz/20250331/66074.html"
  },
  {
    "line_number": 27,
    "text": "2024年剧情动作《误判》BD国粤双语中字",
    "url": "https://www.dytt8.com/html/gndy/dyzz/20250331/66073.html"
  },
  {
    "line_number": 28,
    "text": "2024年奇幻动画《不死者之王剧场版圣王国篇》BD日语中字",
    "url": "https://www.dytt8.com/html/gndy/dyzz/20250330/66069.html"
  },
  {
    "line_number": 29,
    "text": "2024年动画《蓦然回首》HD国日双语中字",
    "url": "https://www.dytt8.com/html/gndy/dyzz/20250329/66068.html"
  },
  {
    "line_number": 30,
    "text": "2024年剧情动作灾难《焚城》HD国粤中英双字",
    "url": "https://www.dytt8.com/html/gndy/dyzz/20250328/66067.html"
  },
  {
    "line_number": 31,
    "text": "2025年惊悚《荷兰镇》BD英语中字",
    "url": "https://www.dytt8.com/html/gndy/dyzz/20250328/66066.html"
  },
  {
    "line_number": 32,
    "text": "2024年恐怖喜剧《诡才之道/鬼才之道》HD国语中字",
    "url": "https://www.dytt8.com/html/gndy/dyzz/20250328/66065.html"
  },
  {
    "line_number": 33,
    "text": "2024年惊悚犯罪《寂静时刻》BD国英双语双字",
    "url": "https://www.dytt8.com/html/gndy/dyzz/20250327/66063.html"
  },
  {
    "line_number": 34,
    "text": "2024年剧情冒险《迷路/征服山的少年》BD中英双字",
    "url": "https://www.dytt8.com/html/gndy/dyzz/20250326/66059.html"
  },
  {
    "line_number": 35,
    "text": "2025年恐怖《怪猴/嗜血怪猴》HD中英双字",
    "url": "https://www.dytt8.com/html/gndy/dyzz/20250326/66058.html"
  },
  {
    "line_number": 36,
    "text": "2025年犯罪喜剧《乌合之众》BD中英双字",
    "url": "https://www.dytt8.com/html/gndy/dyzz/20250325/66057.html"
  },
  {
    "line_number": 37,
    "text": "2025年喜剧《BJ单身日记4》BD中英双字",
    "url": "https://www.dytt8.com/html/gndy/dyzz/20250325/66056.html"
  },
  {
    "line_number": 38,
    "text": "2024年剧情动作《武替道》BD国粤双语中字",
    "url": "https://www.dytt8.com/html/gndy/dyzz/20250323/66051.html"
  },
  {
    "line_number": 39,
    "text": "2024年科幻动画《守望者(下)》BD中英双字",
    "url": "https://www.dytt8.com/html/gndy/dyzz/20250322/66045.html"
  },
  {
    "line_number": 40,
    "text": "2024年科幻动画《守望者(上)》BD中英双字",
    "url": "https://www.dytt8.com/html/gndy/dyzz/20240827/65333.html"
  },
  {
    "line_number": 41,
    "text": "2025年惊悚《最后的呼吸/窒息倒数》BD中英双字",
    "url": "https://www.dytt8.com/html/gndy/dyzz/20250321/66044.html"
  },
  {
    "line_number": 42,
    "text": "2024年惊悚《财富流感》BD中英双字",
    "url": "https://www.dytt8.com/html/gndy/dyzz/20250320/66043.html"
  },
  {
    "line_number": 46,
    "text": "2025年喜剧《亚历山大和他最糟糕的旅程》BD中英双字",
    "url": "https://www.dytt8.com/html/gndy/jddy/20250330/66070.html"
  },
  {
    "line_number": 48,
    "text": "2025年惊悚动作《插翅难飞/高空杀机》BD中英双字",
    "url": "https://www.dytt8.com/html/gndy/jddy/20250328/66064.html"
  },
  {
    "line_number": 49,
    "text": "2025年奇幻喜剧《二龙湖水怪》HD国语中字",
    "url": "https://www.dytt8.com/html/gndy/jddy/20250327/66062.html"
  },
  {
    "line_number": 50,
    "text": "2025年惊悚恐怖《密室逃生》HD国语中字",
    "url": "https://www.dytt8.com/html/gndy/jddy/20250327/66061.html"
  },
  {
    "line_number": 51,
    "text": "2025年奇幻喜剧《闺女特烦恼》HD国语中字",
    "url": "https://www.dytt8.com/html/gndy/jddy/20250324/66055.html"
  },
  {
    "line_number": 52,
    "text": "2025年科幻喜剧《大画王》HD国语中字",
    "url": "https://www.dytt8.com/html/gndy/jddy/20250324/66054.html"
  },
  {
    "line_number": 53,
    "text": "2025年惊悚动作《罪恶清除工》BD中英双字",
    "url": "https://www.dytt8.com/html/gndy/jddy/20250324/66053.html"
  },
  {
    "line_number": 54,
    "text": "2025年悬疑惊悚《来自谁的启示》BD韩语中字",
    "url": "https://www.dytt8.com/html/gndy/jddy/20250323/66052.html"
  },
  {
    "line_number": 55,
    "text": "2025年奇幻《西游降魔篇之快活城》HD国语中字",
    "url": "https://www.dytt8.com/html/gndy/jddy/20250322/66047.html"
  },
  {
    "line_number": 56,
    "text": "2025年剧情犯罪《恶行之外》HD国粤双语中字",
    "url": "https://www.dytt8.com/html/gndy/jddy/20250322/66046.html"
  },
  {
    "line_number": 57,
    "text": "2024年动作恐怖《复活之战/尸控战场》BD中字",
    "url": "https://www.dytt8.com/html/gndy/jddy/20250320/66042.html"
  },
  {
    "line_number": 58,
    "text": "2025年悬疑恐怖《腥心眼/心眼杀手》BD中英双字",
    "url": "https://www.dytt8.com/html/gndy/jddy/20250319/66040.html"
  },
  {
    "line_number": 59,
    "text": "2023年剧情犯罪《对外秘密：权力的诞生》BD韩语中字",
    "url": "https://www.dytt8.com/html/gndy/jddy/20250318/66038.html"
  },
  {
    "line_number": 60,
    "text": "2025年科幻动作《恶兽》HD国语中字",
    "url": "https://www.dytt8.com/html/gndy/jddy/20250318/66037.html"
  },
  {
    "line_number": 61,
    "text": "2025年动作喜剧《前任杀神》BD中字",
    "url": "https://www.dytt8.com/html/gndy/jddy/20250318/66036.html"
  },
  {
    "line_number": 62,
    "text": "2025年惊悚恐怖《临界点》BD中英双字",
    "url": "https://www.dytt8.com/html/gndy/jddy/20250317/66035.html"
  },
  {
    "line_number": 63,
    "text": "2025年奇幻动作《奇怪的记忆》HD国语中字",
    "url": "https://www.dytt8.com/html/gndy/jddy/20250316/66033.html"
  },
  {
    "line_number": 64,
    "text": "2025年动作恐怖《静默地带/丧尸静默区》BD中英双字",
    "url": "https://www.dytt8.com/html/gndy/jddy/20250316/66032.html"
  },
  {
    "line_number": 67,
    "text": "更多>>",
    "url": "https://www.dytt8.com/html/tv/hytv/"
  },
  {
    "line_number": 68,
    "text": "[华语剧集专区",
    "url": "https://www.dytt8.com/html/tv/hytv/"
  },
  {
    "line_number": 106,
    "text": "2025年科幻动作《夜魔侠：重生 第一季》更新05-06集中英",
    "url": "https://www.dytt8.com/html/tv/oumeitv/20250307/66006.html"
  },
  {
    "line_number": 108,
    "text": "2025年科幻悬疑《人生切割术 第二季》全10集中英双字[本",
    "url": "https://www.dytt8.com/html/tv/oumeitv/20250120/65826.html"
  },
  {
    "line_number": 109,
    "text": "2024年科幻悬疑《末日地堡 第二季》更新全10集中英双字",
    "url": "https://www.dytt8.com/html/tv/oumeitv/20241126/65629.html"
  },
  {
    "line_number": 110,
    "text": "2025年动作《驯荒记/美国狂野》全6集1080P中英双字",
    "url": "https://www.dytt8.com/html/tv/oumeitv/20250111/65800.html"
  },
  {
    "line_number": 111,
    "text": "2024年科幻动作《沙丘：预言 第一季》全6集中英双字",
    "url": "https://www.dytt8.com/html/tv/oumeitv/20241118/65607.html"
  },
  {
    "line_number": 112,
    "text": "2024年惊悚《豺狼的日子 第一季》更新全10集中英双字",
    "url": "https://www.dytt8.com/html/tv/oumeitv/20241116/65596.html"
  },
  {
    "line_number": 113,
    "text": "2024年动作《特别行动：母狮 第二季》更新01-08集中英双",
    "url": "https://www.dytt8.com/html/tv/oumeitv/20241101/65551.html"
  },
  {
    "line_number": 114,
    "text": "2024年科幻《英雄联盟：双城之战 第二季》全9集中英双字",
    "url": "https://www.dytt8.com/html/tv/oumeitv/20241116/65598.html"
  },
  {
    "line_number": 115,
    "text": "2024年剧情《塔尔萨之王 第二季》全10集中英双字",
    "url": "https://www.dytt8.com/html/tv/oumeitv/20240923/65427.html"
  },
  {
    "line_number": 116,
    "text": "2024年奇幻《企鹅人第一季》全8集中英双字",
    "url": "https://www.dytt8.com/html/tv/oumeitv/20240923/65426.html"
  },
  {
    "line_number": 117,
    "text": "2024年科幻《女巫阿加莎 第一季》全9集中英双字",
    "url": "https://www.dytt8.com/html/tv/oumeitv/20240923/65428.html"
  },
  {
    "line_number": 118,
    "text": "2024年恐怖《行尸走肉：达里尔·迪克森 第二季》更新01-",
    "url": "https://www.dytt8.com/html/tv/oumeitv/20241002/65454.html"
  },
  {
    "line_number": 119,
    "text": "2024年惊悚《流人/翻盘特工队 第四季》全6集中英双字",
    "url": "https://www.dytt8.com/html/tv/oumeitv/20240905/65373.html"
  },
  {
    "line_number": 120,
    "text": "2024年奇幻动作《指环王：力量之戒 第二季》全8集中英双",
    "url": "https://www.dytt8.com/html/tv/oumeitv/20240831/65347.html"
  },
  {
    "line_number": 123,
    "text": "![阳光电影",
    "url": "https://www.dytt8.com/images/bbs_btn.gif"
  },
  {
    "line_number": 125,
    "text": "2024年沈腾马丽喜剧《抓娃娃",
    "url": "https://www.dytt8.com/html/gndy/dyzz/20240927/65439.html"
  },
  {
    "line_number": 125,
    "text": "2024年剧情爱情《负负得正》",
    "url": "https://www.dytt8.com/html/gndy/dyzz/20240927/65438.html"
  },
  {
    "line_number": 125,
    "text": "2023年剧情《乘船而去》BD国",
    "url": "https://www.dytt8.com/html/gndy/dyzz/20240925/65433.html"
  },
  {
    "line_number": 125,
    "text": "2023年获奖剧情《白日之下》",
    "url": "https://www.dytt8.com/html/gndy/dyzz/20240923/65431.html"
  },
  {
    "line_number": 125,
    "text": "2024年疑惊悚《劫机/劫机197",
    "url": "https://www.dytt8.com/html/gndy/dyzz/20240922/65425.html"
  },
  {
    "line_number": 125,
    "text": "2024年获奖剧情《图腾/女孩",
    "url": "https://www.dytt8.com/html/gndy/dyzz/20240922/65424.html"
  },
  {
    "line_number": 125,
    "text": "2024年高分剧情《姥姥的外孙",
    "url": "https://www.dytt8.com/html/gndy/dyzz/20240914/65404.html"
  },
  {
    "line_number": 125,
    "text": "2023年剧情《孤注一掷》HD国",
    "url": "https://www.dytt8.com/html/gndy/dyzz/20240914/65403.html"
  },
  {
    "line_number": 125,
    "text": "2024年动画喜剧《头脑特工队",
    "url": "https://www.dytt8.com/html/gndy/dyzz/20240913/65395.html"
  },
  {
    "line_number": 125,
    "text": "2024年动作喜剧《绝地战警：",
    "url": "https://www.dytt8.com/html/gndy/dyzz/20240912/65393.html"
  },
  {
    "line_number": 125,
    "text": "2024年动作惊悚《逆岭/叛军",
    "url": "https://www.dytt8.com/html/gndy/dyzz/20240910/65388.html"
  },
  {
    "line_number": 125,
    "text": "2023年获奖剧情《富都青年》",
    "url": "https://www.dytt8.com/html/gndy/dyzz/20240910/65387.html"
  },
  {
    "line_number": 125,
    "text": "2024年科幻喜剧《从21世纪安",
    "url": "https://www.dytt8.com/html/gndy/dyzz/20240907/65381.html"
  },
  {
    "line_number": 125,
    "text": "2024年动作惊悚《因果报应/",
    "url": "https://www.dytt8.com/html/gndy/dyzz/20240906/65374.html"
  },
  {
    "line_number": 125,
    "text": "2024年剧情喜剧《飞驰人生2",
    "url": "https://www.dytt8.com/html/gndy/dyzz/20240429/64942.html"
  },
  {
    "line_number": 125,
    "text": "2024年动作喜剧《城市猎人》",
    "url": "https://www.dytt8.com/html/gndy/dyzz/20240428/64939.html"
  },
  {
    "line_number": 125,
    "text": "2024年剧情喜剧《热辣滚烫》",
    "url": "https://www.dytt8.com/html/gndy/dyzz/20240418/64905.html"
  },
  {
    "line_number": 125,
    "text": "2023年动作《碟中谍7：致命",
    "url": "https://www.dytt8.com/html/gndy/dyzz/20231001/64184.html"
  },
  {
    "line_number": 125,
    "text": "2023年动作《GT赛车：极速狂",
    "url": "https://www.dytt8.com/html/gndy/dyzz/20230927/64171.html"
  },
  {
    "line_number": 125,
    "text": "2022年动画奇幻《铃芽之旅》",
    "url": "https://www.dytt8.com/html/gndy/dyzz/20230924/64162.html"
  },
  {
    "line_number": 125,
    "text": "2023年动作奇幻《封神第一部",
    "url": "https://www.dytt8.com/html/gndy/dyzz/20230922/64156.html"
  },
  {
    "line_number": 125,
    "text": "2023年科幻动作《蓝甲虫》BD",
    "url": "https://www.dytt8.com/html/gndy/dyzz/20230920/64151.html"
  },
  {
    "line_number": 125,
    "text": "2023年喜剧动画《疯狂元素城",
    "url": "https://www.dytt8.com/html/gndy/dyzz/20230920/64149.html"
  },
  {
    "line_number": 125,
    "text": "2023年喜剧动画《茶啊二中》",
    "url": "https://www.dytt8.com/html/gndy/dyzz/20230919/64145.html"
  },
  {
    "line_number": 125,
    "text": "2023年剧情爱情《初见倾心/",
    "url": "https://www.dytt8.com/html/gndy/dyzz/20230918/64140.html"
  },
  {
    "line_number": 125,
    "text": "2023年惊悚恐怖《回应我》BD",
    "url": "https://www.dytt8.com/html/gndy/dyzz/20230914/64125.html"
  },
  {
    "line_number": 125,
    "text": "2023年剧情爱情《我的错误》",
    "url": "https://www.dytt8.com/html/gndy/dyzz/20230913/64120.html"
  },
  {
    "line_number": 125,
    "text": "2023年科幻动画《忍者神龟：",
    "url": "https://www.dytt8.com/html/gndy/dyzz/20230907/64102.html"
  },
  {
    "line_number": 125,
    "text": "2023年喜剧奇幻《芭比》HD英",
    "url": "https://www.dytt8.com/html/gndy/dyzz/20230905/64097.html"
  },
  {
    "line_number": 125,
    "text": "2023年喜剧爱情《星条红与皇",
    "url": "https://www.dytt8.com/html/gndy/dyzz/20230905/64095.html"
  },
  {
    "line_number": 125,
    "text": "2023年剧情传记《气垫传奇》",
    "url": "https://www.dytt8.com/html/gndy/dyzz/20230904/64093.html"
  },
  {
    "line_number": 125,
    "text": "2023年动作《夺宝奇兵5：命",
    "url": "https://www.dytt8.com/html/gndy/dyzz/20230829/64079.html"
  },
  {
    "line_number": 125,
    "text": "2023年剧情悬疑《无名》BD国",
    "url": "https://www.dytt8.com/html/gndy/dyzz/20230828/64076.html"
  },
  {
    "line_number": 128,
    "text": "任达华邱淑贞动作《我是一个贼",
    "url": "https://www.dytt8.com/html/gndy/jddy/20230606/63791.html"
  },
  {
    "line_number": 128,
    "text": "2007年剧情惊悚《门徒》BD国粤",
    "url": "https://www.dytt8.com/html/gndy/jddy/20230525/63753.html"
  },
  {
    "line_number": 128,
    "text": "2023年惊悚动作《帕坦》BD中英",
    "url": "https://www.dytt8.com/html/gndy/jddy/20230415/63619.html"
  },
  {
    "line_number": 128,
    "text": "2023年剧情惊悚《瞒天劫》BD中",
    "url": "https://www.dytt8.com/html/gndy/jddy/20230404/63584.html"
  },
  {
    "line_number": 128,
    "text": "2017年动作《不汗党：地下秩序",
    "url": "https://www.dytt8.com/html/gndy/jddy/20230310/63502.html"
  },
  {
    "line_number": 128,
    "text": "2022年科幻《新·奥特曼》HD日",
    "url": "https://www.dytt8.com/html/gndy/jddy/20221119/63170.html"
  },
  {
    "line_number": 128,
    "text": "2022年奇幻悬疑动作《暗夜狼人",
    "url": "https://www.dytt8.com/html/gndy/jddy/20221013/63057.html"
  },
  {
    "line_number": 128,
    "text": "高分获奖《细细的红线/红色警",
    "url": "https://www.dytt8.com/html/gndy/jddy/20220221/62347.html"
  },
  {
    "line_number": 128,
    "text": "2022年悬疑剧情动画《房子》BD",
    "url": "https://www.dytt8.com/html/gndy/jddy/20220204/62294.html"
  },
  {
    "line_number": 128,
    "text": "2021年剧情《浊水漂流》BD粤语",
    "url": "https://www.dytt8.com/html/gndy/jddy/20220201/62282.html"
  },
  {
    "line_number": 128,
    "text": "2018年悬疑动作《无双》BD国粤",
    "url": "https://www.dytt8.com/html/gndy/jddy/20211023/61979.html"
  },
  {
    "line_number": 128,
    "text": "2015年高分获奖争《无境之兽》",
    "url": "https://www.dytt8.com/html/gndy/jddy/20211010/61938.html"
  },
  {
    "line_number": 131,
    "text": "2025年内地电视剧《棋士》第05",
    "url": "https://www.dytt8.com/html/tv/hytv/20250330/66072.html"
  },
  {
    "line_number": 131,
    "text": "2025年内地电视剧《念无双》第",
    "url": "https://www.dytt8.com/html/tv/hytv/20250330/66071.html"
  },
  {
    "line_number": 131,
    "text": "2025年内地电视剧《雁回时》第",
    "url": "https://www.dytt8.com/html/tv/hytv/20250323/66050.html"
  },
  {
    "line_number": 131,
    "text": "2025年内地电视剧《黄雀》第24",
    "url": "https://www.dytt8.com/html/tv/hytv/20250322/66049.html"
  },
  {
    "line_number": 131,
    "text": "2025年内地电视剧《燃罪》第38",
    "url": "https://www.dytt8.com/html/tv/hytv/20250322/66048.html"
  },
  {
    "line_number": 131,
    "text": "2025年内地电视剧《嘘，国王在",
    "url": "https://www.dytt8.com/html/tv/hytv/20250315/66030.html"
  },
  {
    "line_number": 131,
    "text": "2025年内地电视剧《北上》第38",
    "url": "https://www.dytt8.com/html/tv/hytv/20250310/66014.html"
  },
  {
    "line_number": 131,
    "text": "2025年内地电视剧《似锦》第40",
    "url": "https://www.dytt8.com/html/tv/hytv/20250308/66007.html"
  },
  {
    "line_number": 131,
    "text": "2025年内地电视剧《爱你》第28",
    "url": "https://www.dytt8.com/html/tv/hytv/20250302/65977.html"
  },
  {
    "line_number": 131,
    "text": "2025年内地电视剧《滤镜》第32",
    "url": "https://www.dytt8.com/html/tv/hytv/20250302/65976.html"
  },
  {
    "line_number": 131,
    "text": "2025年内地电视剧《180天重启",
    "url": "https://www.dytt8.com/html/tv/hytv/20250223/65958.html"
  },
  {
    "line_number": 131,
    "text": "2025年内地电视剧《难哄》第32",
    "url": "https://www.dytt8.com/html/tv/hytv/20250222/65953.html"
  },
  {
    "line_number": 131,
    "text": "2025年内地电视剧《树下有片红",
    "url": "https://www.dytt8.com/html/tv/hytv/20250222/65952.html"
  },
  {
    "line_number": 131,
    "text": "2025年内地电视剧《怎敌她千娇",
    "url": "https://www.dytt8.com/html/tv/hytv/20250216/65936.html"
  },
  {
    "line_number": 131,
    "text": "2025年内地电视剧《余烬之上》",
    "url": "https://www.dytt8.com/html/tv/hytv/20250216/65935.html"
  },
  {
    "line_number": 131,
    "text": "2025年内地电视剧《掌心》第30",
    "url": "https://www.dytt8.com/html/tv/hytv/20250216/65934.html"
  },
  {
    "line_number": 131,
    "text": "2025年内地电视剧《仙台有树》",
    "url": "https://www.dytt8.com/html/tv/hytv/20250216/65933.html"
  },
  {
    "line_number": 131,
    "text": "2025年内地电视剧《六姊妹》第",
    "url": "https://www.dytt8.com/html/tv/hytv/20250209/65905.html"
  },
  {
    "line_number": 131,
    "text": "2025年内地电视剧《漫影寻踪》",
    "url": "https://www.dytt8.com/html/tv/hytv/20250208/65904.html"
  },
  {
    "line_number": 134,
    "text": "2025年韩国Netflix《许餐厅》",
    "url": "https://www.dytt8.com/html/tv/rihantv/20250327/66060.html"
  },
  {
    "line_number": 134,
    "text": "2025年韩国JTBC《协商的技术》",
    "url": "https://www.dytt8.com/html/tv/rihantv/20250312/66019.html"
  },
  {
    "line_number": 134,
    "text": "2025年韩国GENIETV《接送人生",
    "url": "https://www.dytt8.com/html/tv/rihantv/20250305/65997.html"
  },
  {
    "line_number": 134,
    "text": "2025年韩国TVN《爱情发芽中》",
    "url": "https://www.dytt8.com/html/tv/rihantv/20250304/65988.html"
  },
  {
    "line_number": 134,
    "text": "2025年韩国Watcha《秘密关系》",
    "url": "https://www.dytt8.com/html/tv/rihantv/20250228/65975.html"
  },
  {
    "line_number": 134,
    "text": "2025年韩国Disney+《宝物岛》",
    "url": "https://www.dytt8.com/html/tv/rihantv/20250224/65964.html"
  },
  {
    "line_number": 134,
    "text": "2025年韩国MBC《卧底高中》第1",
    "url": "https://www.dytt8.com/html/tv/rihantv/20250224/65963.html"
  },
  {
    "line_number": 134,
    "text": "2025年韩国TVN《那家伙是黑炎",
    "url": "https://www.dytt8.com/html/tv/rihantv/20250220/65948.html"
  },
  {
    "line_number": 134,
    "text": "2025年韩国ChannelA《魔女》第",
    "url": "https://www.dytt8.com/html/tv/rihantv/20250217/65938.html"
  },
  {
    "line_number": 134,
    "text": "2025年韩国U+ Mobile TV《善意",
    "url": "https://www.dytt8.com/html/tv/rihantv/20250211/65916.html"
  },
  {
    "line_number": 134,
    "text": "2025年韩国COUPANG PLAY《新乌",
    "url": "https://www.dytt8.com/html/tv/rihantv/20250210/65908.html"
  },
  {
    "line_number": 134,
    "text": "2025年韩国KBS《喀喀喀喀》第1",
    "url": "https://www.dytt8.com/html/tv/rihantv/20250210/65907.html"
  },
  {
    "line_number": 134,
    "text": "2025年韩国TVING《春画恋爱谈",
    "url": "https://www.dytt8.com/html/tv/rihantv/20250210/65906.html"
  },
  {
    "line_number": 134,
    "text": "2025年韩国Disney+《揭密最前",
    "url": "https://www.dytt8.com/html/tv/rihantv/20250118/65822.html"
  },
  {
    "line_number": 134,
    "text": "2025年韩国MBC《加利福尼亚旅",
    "url": "https://www.dytt8.com/html/tv/rihantv/20250112/65805.html"
  },
  {
    "line_number": 134,
    "text": "2025年韩国TVN《元敬》第12集[",
    "url": "https://www.dytt8.com/html/tv/rihantv/20250108/65777.html"
  },
  {
    "line_number": 137,
    "text": "2024年科幻《女巫阿加莎 第",
    "url": "https://www.dytt8.com/html/tv/oumeitv/20240923/65428.html"
  },
  {
    "line_number": 137,
    "text": "2024年剧情《塔尔萨之王 第",
    "url": "https://www.dytt8.com/html/tv/oumeitv/20240923/65427.html"
  },
  {
    "line_number": 137,
    "text": "2024年奇幻《企鹅人第一季》",
    "url": "https://www.dytt8.com/html/tv/oumeitv/20240923/65426.html"
  },
  {
    "line_number": 137,
    "text": "2024年惊悚《流人/翻盘特工",
    "url": "https://www.dytt8.com/html/tv/oumeitv/20240905/65373.html"
  },
  {
    "line_number": 137,
    "text": "2024年奇幻动作《指环王：力",
    "url": "https://www.dytt8.com/html/tv/oumeitv/20240831/65347.html"
  },
  {
    "line_number": 137,
    "text": "2024年悬疑《无罪的罪人/无",
    "url": "https://www.dytt8.com/html/tv/oumeitv/20240617/65104.html"
  },
  {
    "line_number": 137,
    "text": "2024年奇幻动作《龙之家族 ",
    "url": "https://www.dytt8.com/html/tv/oumeitv/20240617/65103.html"
  },
  {
    "line_number": 137,
    "text": "2024年战争冒险《幕府将军 ",
    "url": "https://www.dytt8.com/html/tv/oumeitv/20240229/64711.html"
  },
  {
    "line_number": 137,
    "text": "2024年科幻动作《光环 第二",
    "url": "https://www.dytt8.com/html/tv/oumeitv/20240220/64682.html"
  },
  {
    "line_number": 137,
    "text": "2024年动作战争《空战群英 ",
    "url": "https://www.dytt8.com/html/tv/oumeitv/20240128/64601.html"
  },
  {
    "line_number": 137,
    "text": "2024年悬疑惊悚《真探 第四",
    "url": "https://www.dytt8.com/html/tv/oumeitv/20240115/64546.html"
  },
  {
    "line_number": 137,
    "text": "2023年科幻动作《波西·杰克",
    "url": "https://www.dytt8.com/html/tv/oumeitv/20231223/64463.html"
  },
  {
    "line_number": 137,
    "text": "2023年科幻动作《帝王计划：",
    "url": "https://www.dytt8.com/html/tv/oumeitv/20231118/64351.html"
  },
  {
    "line_number": 137,
    "text": "2023年科幻动作《洛基 第二",
    "url": "https://www.dytt8.com/html/tv/oumeitv/20231007/64207.html"
  },
  {
    "line_number": 137,
    "text": "2023年动作《大陆酒店/刺客",
    "url": "https://www.dytt8.com/html/tv/oumeitv/20230924/64164.html"
  },
  {
    "line_number": 137,
    "text": "2023年美剧《行尸走肉：达里",
    "url": "https://www.dytt8.com/html/tv/oumeitv/20230913/64121.html"
  },
  {
    "line_number": 137,
    "text": "2023年科幻动作《阿索卡 第",
    "url": "https://www.dytt8.com/html/tv/oumeitv/20230824/64061.html"
  },
  {
    "line_number": 137,
    "text": "2023年美剧《特别行动：母狮",
    "url": "https://www.dytt8.com/html/tv/oumeitv/20230725/63958.html"
  },
  {
    "line_number": 137,
    "text": "2023年美剧《火线警探：原始",
    "url": "https://www.dytt8.com/html/tv/oumeitv/20230720/63941.html"
  },
  {
    "line_number": 140,
    "text": "综艺大热门-20250304~20250325",
    "url": "https://www.dytt8.com/html/zongyi2013/taiwanzongyi/20250306/66002.html"
  },
  {
    "line_number": 142,
    "text": "11点热吵店-20250303~20250325",
    "url": "https://www.dytt8.com/html/zongyi2013/taiwanzongyi/20250306/66001.html"
  },
  {
    "line_number": 143,
    "text": "型男大主厨-20250303~20250325",
    "url": "https://www.dytt8.com/html/zongyi2013/taiwanzongyi/20250305/65996.html"
  },
  {
    "line_number": 144,
    "text": "综艺玩很大-20250302~20250323",
    "url": "https://www.dytt8.com/html/zongyi2013/taiwanzongyi/20250305/65995.html"
  },
  {
    "line_number": 145,
    "text": "认识的哥哥-20250301~20250322",
    "url": "https://www.dytt8.com/html/zongyi2013/qitazongyi/20250303/65981.html"
  },
  {
    "line_number": 146,
    "text": "惊人的星期六-20250301~20250322",
    "url": "https://www.dytt8.com/html/zongyi2013/qitazongyi/20250303/65980.html"
  },
  {
    "line_number": 147,
    "text": "我独自生活-20250307~20250321",
    "url": "https://www.dytt8.com/html/zongyi2013/qitazongyi/20250312/66021.html"
  },
  {
    "line_number": 148,
    "text": "威廉沈欢乐送-20250307~20250321",
    "url": "https://www.dytt8.com/html/zongyi2013/taiwanzongyi/20250312/66020.html"
  },
  {
    "line_number": 149,
    "text": "Running Man-20250302~20250323",
    "url": "https://www.dytt8.com/html/zongyi2013/qitazongyi/20250305/65992.html"
  },
  {
    "line_number": 150,
    "text": "两天一夜第四季-20250302~20250323",
    "url": "https://www.dytt8.com/html/zongyi2013/qitazongyi/20250305/65991.html"
  },
  {
    "line_number": 151,
    "text": "我家的熊孩子-20250302~20250323",
    "url": "https://www.dytt8.com/html/zongyi2013/qitazongyi/20250305/65993.html"
  },
  {
    "line_number": 152,
    "text": "娱乐百分百-20250305~20250320",
    "url": "https://www.dytt8.com/html/zongyi2013/taiwanzongyi/20250307/66005.html"
  },
  {
    "line_number": 153,
    "text": "美好的一天-20250302~20250316",
    "url": "https://www.dytt8.com/html/zongyi2013/qitazongyi/20250305/65994.html"
  },
  {
    "line_number": 154,
    "text": "超人回来了-20250305~20250312",
    "url": "https://www.dytt8.com/html/zongyi2013/qitazongyi/20250309/66010.html"
  },
  {
    "line_number": 155,
    "text": "威廉沈欢乐送-20250207~20250228",
    "url": "https://www.dytt8.com/html/zongyi2013/taiwanzongyi/20250211/65918.html"
  },
  {
    "line_number": 156,
    "text": "综艺大热门-20250204~20250228",
    "url": "https://www.dytt8.com/html/zongyi2013/taiwanzongyi/20250207/65899.html"
  },
  {
    "line_number": 160,
    "text": "凡人修仙传 外海风云 第12话",
    "url": "https://www.dytt8.com/html/dongman/20250210/65910.html"
  },
  {
    "line_number": 162,
    "text": "吞噬星空 第6季 第08话",
    "url": "https://www.dytt8.com/html/dongman/new/20250210/65909.html"
  },
  {
    "line_number": 163,
    "text": "完美世界第五季 第26话",
    "url": "https://www.dytt8.com/html/dongman/new/20241202/65649.html"
  },
  {
    "line_number": 164,
    "text": "我独自升级 第二季 第13话",
    "url": "https://www.dytt8.com/html/dongman/new/20250108/65781.html"
  },
  {
    "line_number": 165,
    "text": "MOMENTARY LILY 第13话",
    "url": "https://www.dytt8.com/html/dongman/new/20250108/65779.html"
  },
  {
    "line_number": 166,
    "text": "黄昏旅店 第12话",
    "url": "https://www.dytt8.com/html/dongman/new/20250108/65783.html"
  },
  {
    "line_number": 167,
    "text": "一杆青空 第12话",
    "url": "https://www.dytt8.com/html/dongman/new/20250108/65782.html"
  },
  {
    "line_number": 168,
    "text": "青之驱魔师终夜篇 第12话",
    "url": "https://www.dytt8.com/html/dongman/new/20250108/65780.html"
  },
  {
    "line_number": 169,
    "text": "名侦探柯南 第1201~1215话",
    "url": "https://www.dytt8.com/html/dongman/20241126/65631.html"
  },
  {
    "line_number": 170,
    "text": "龙珠大魔 第20话",
    "url": "https://www.dytt8.com/html/dongman/20241029/65543.html"
  },
  {
    "line_number": 174,
    "text": "经典单机游戏《残酷谎言8：最终嫌疑》中文版",
    "url": "https://www.dytt8.com/html/game/jingdianyouxifabu/20180127/56207.html"
  },
  {
    "line_number": 176,
    "text": "经典单机游戏《轩辕伏魔录》中文版",
    "url": "https://www.dytt8.com/html/game/jingdianyouxifabu/20180127/56206.html"
  },
  {
    "line_number": 177,
    "text": "经典单机游戏《模拟火车2014》中文版",
    "url": "https://www.dytt8.com/html/game/jingdianyouxifabu/20180127/56205.html"
  },
  {
    "line_number": 178,
    "text": "经典单机游戏《世嘉创世经典游戏合集》硬盘版",
    "url": "https://www.dytt8.com/html/game/jingdianyouxifabu/20180127/56204.html"
  },
  {
    "line_number": 179,
    "text": "经典单机游戏《经典街机游戏》硬盘版",
    "url": "https://www.dytt8.com/html/game/jingdianyouxifabu/20180126/56198.html"
  },
  {
    "line_number": 180,
    "text": "经典单机游戏《合金弹头：完整版》硬盘版",
    "url": "https://www.dytt8.com/html/game/jingdianyouxifabu/20180126/56197.html"
  },
  {
    "line_number": 181,
    "text": "经典单机游戏《侠盗猎车手3》中文版",
    "url": "https://www.dytt8.com/html/game/jingdianyouxifabu/20180126/56196.html"
  },
  {
    "line_number": 182,
    "text": "经典单机游戏《荒岛求生》中文版",
    "url": "https://www.dytt8.com/html/game/jingdianyouxifabu/20180126/56195.html"
  },
  {
    "line_number": 183,
    "text": "经典单机游戏《玩具塔防4：星海战争》硬盘版",
    "url": "https://www.dytt8.com/html/game/jingdianyouxifabu/20180125/56190.html"
  },
  {
    "line_number": 184,
    "text": "经典单机游戏《搏击长空：风暴突击队》硬盘版",
    "url": "https://www.dytt8.com/html/game/jingdianyouxifabu/20180125/56189.html"
  },
  {
    "line_number": 185,
    "text": "经典单机游戏《使命召唤7：黑色行动》中文版",
    "url": "https://www.dytt8.com/html/game/jingdianyouxifabu/20180125/56188.html"
  },
  {
    "line_number": 186,
    "text": "经典单机游戏《帝国时代2：征服者》中文版",
    "url": "https://www.dytt8.com/html/game/jingdianyouxifabu/20180125/56187.html"
  },
  {
    "line_number": 187,
    "text": "经典单机游戏《合金装备5：原爆点》硬盘版",
    "url": "https://www.dytt8.com/html/game/jingdianyouxifabu/20180124/56185.html"
  },
  {
    "line_number": 188,
    "text": "经典单机游戏《最终幻想13：2》繁体版",
    "url": "https://www.dytt8.com/html/game/jingdianyouxifabu/20180124/56184.html"
  },
  {
    "line_number": 192,
    "text": "我独自生活-20250307~20250",
    "url": "https://www.dytt8.com/html/zongyi2013/qitazongyi/20250312/66021.html"
  },
  {
    "line_number": 192,
    "text": "威廉沈欢乐送-20250307~202",
    "url": "https://www.dytt8.com/html/zongyi2013/taiwanzongyi/20250312/66020.html"
  },
  {
    "line_number": 192,
    "text": "超人回来了-20250305~20250",
    "url": "https://www.dytt8.com/html/zongyi2013/qitazongyi/20250309/66010.html"
  },
  {
    "line_number": 192,
    "text": "娱乐百分百-20250305~20250",
    "url": "https://www.dytt8.com/html/zongyi2013/taiwanzongyi/20250307/66005.html"
  },
  {
    "line_number": 192,
    "text": "综艺大热门-20250304~20250",
    "url": "https://www.dytt8.com/html/zongyi2013/taiwanzongyi/20250306/66002.html"
  },
  {
    "line_number": 192,
    "text": "11点热吵店-20250303~20250",
    "url": "https://www.dytt8.com/html/zongyi2013/taiwanzongyi/20250306/66001.html"
  },
  {
    "line_number": 192,
    "text": "型男大主厨-20250303~20250",
    "url": "https://www.dytt8.com/html/zongyi2013/taiwanzongyi/20250305/65996.html"
  },
  {
    "line_number": 192,
    "text": "综艺玩很大-20250302~20250",
    "url": "https://www.dytt8.com/html/zongyi2013/taiwanzongyi/20250305/65995.html"
  },
  {
    "line_number": 192,
    "text": "美好的一天-20250302~20250",
    "url": "https://www.dytt8.com/html/zongyi2013/qitazongyi/20250305/65994.html"
  },
  {
    "line_number": 192,
    "text": "我家的熊孩子-20250302~202",
    "url": "https://www.dytt8.com/html/zongyi2013/qitazongyi/20250305/65993.html"
  },
  {
    "line_number": 192,
    "text": "Running Man-20250302~2025",
    "url": "https://www.dytt8.com/html/zongyi2013/qitazongyi/20250305/65992.html"
  },
  {
    "line_number": 192,
    "text": "两天一夜第四季-20250302~2",
    "url": "https://www.dytt8.com/html/zongyi2013/qitazongyi/20250305/65991.html"
  },
  {
    "line_number": 192,
    "text": "认识的哥哥-20250301~20250",
    "url": "https://www.dytt8.com/html/zongyi2013/qitazongyi/20250303/65981.html"
  },
  {
    "line_number": 192,
    "text": "惊人的星期六-20250301~202",
    "url": "https://www.dytt8.com/html/zongyi2013/qitazongyi/20250303/65980.html"
  },
  {
    "line_number": 192,
    "text": "美好的一天-20250216~20250",
    "url": "https://www.dytt8.com/html/zongyi2013/qitazongyi/20250220/65949.html"
  },
  {
    "line_number": 192,
    "text": "综艺玩很大-20250209~20250",
    "url": "https://www.dytt8.com/html/zongyi2013/taiwanzongyi/20250214/65926.html"
  },
  {
    "line_number": 192,
    "text": "我独自生活-20250207~20250",
    "url": "https://www.dytt8.com/html/zongyi2013/qitazongyi/20250212/65920.html"
  },
  {
    "line_number": 192,
    "text": "超人回来了-20250205~20250",
    "url": "https://www.dytt8.com/html/zongyi2013/qitazongyi/20250212/65919.html"
  },
  {
    "line_number": 192,
    "text": "威廉沈欢乐送-20250207~202",
    "url": "https://www.dytt8.com/html/zongyi2013/taiwanzongyi/20250211/65918.html"
  },
  {
    "line_number": 195,
    "text": "杂旅-That’s Journey- 第01话",
    "url": "https://www.dytt8.com/html/dongman/20250303/65982.html"
  },
  {
    "line_number": 195,
    "text": "死神千年血战篇相克谭 第14话",
    "url": "https://www.dytt8.com/html/dongman/20241028/65540.html"
  },
  {
    "line_number": 195,
    "text": "伍六七之记忆碎片 第10话",
    "url": "https://www.dytt8.com/html/dongman/20241028/65539.html"
  },
  {
    "line_number": 195,
    "text": "吞噬星空 第5季 第26话",
    "url": "https://www.dytt8.com/html/dongman/new/20241015/65506.html"
  },
  {
    "line_number": 195,
    "text": "剑来 第26话",
    "url": "https://www.dytt8.com/html/dongman/new/20240902/65361.html"
  },
  {
    "line_number": 198,
    "text": "经典单机游戏《明星三缺一》硬",
    "url": "https://www.dytt8.com/html/game/jingdianyouxifabu/20171230/55916.html"
  },
  {
    "line_number": 198,
    "text": "经典单机游戏《上古空间》PC版",
    "url": "https://www.dytt8.com/html/game/jingdianyouxifabu/20170704/54421.html"
  },
  {
    "line_number": 198,
    "text": "经典单机游戏《反抗小队》PC版",
    "url": "https://www.dytt8.com/html/game/jingdianyouxifabu/20170411/53718.html"
  },
  {
    "line_number": 198,
    "text": "经典单机游戏《世界的命运：临",
    "url": "https://www.dytt8.com/html/game/jingdianyouxifabu/20170319/53520.html"
  },
  {
    "line_number": 198,
    "text": "经典单机游戏《失落编年史2：",
    "url": "https://www.dytt8.com/html/game/jingdianyouxifabu/20161230/52851.html"
  },
  {
    "line_number": 198,
    "text": "经典单机游戏《旅法师对决2013",
    "url": "https://www.dytt8.com/html/game/jingdianyouxifabu/20161230/52848.html"
  },
  {
    "line_number": 198,
    "text": "经典单机游戏《世纪之石》简体",
    "url": "https://www.dytt8.com/html/game/jingdianyouxifabu/20161219/52773.html"
  },
  {
    "line_number": 198,
    "text": "经典单机游戏《特里克迷失的眼",
    "url": "https://www.dytt8.com/html/game/jingdianyouxifabu/20161119/52534.html"
  },
  {
    "line_number": 198,
    "text": "热门单机游戏《恶魔城：暗影之",
    "url": "https://www.dytt8.com/html/game/remenyouxi/20140420/44947.html"
  },
  {
    "line_number": 198,
    "text": "热门单机游戏《反恐重击：隐秘",
    "url": "https://www.dytt8.com/html/game/remenyouxi/20140420/44946.html"
  },
  {
    "line_number": 198,
    "text": "热门单机游戏《重返德军总部：",
    "url": "https://www.dytt8.com/html/game/remenyouxi/20140217/44449.html"
  },
  {
    "line_number": 198,
    "text": "热门单机游戏《战地1942：秘密",
    "url": "https://www.dytt8.com/html/game/remenyouxi/20140216/44442.html"
  },
  {
    "line_number": 198,
    "text": "热门单机游戏《生化奇兵2》中",
    "url": "https://www.dytt8.com/html/game/remenyouxi/20140214/44423.html"
  },
  {
    "line_number": 198,
    "text": "热门单机游戏《明星三缺一》中",
    "url": "https://www.dytt8.com/html/game/remenyouxi/20140213/44417.html"
  },
  {
    "line_number": 198,
    "text": "热门单机游戏《梦幻麻将馆4：",
    "url": "https://www.dytt8.com/html/game/remenyouxi/20140202/44315.html"
  },
  {
    "line_number": 198,
    "text": "热门单机游戏《红色警戒2：尤",
    "url": "https://www.dytt8.com/html/game/remenyouxi/20140202/44314.html"
  },
  {
    "line_number": 204,
    "text": "网站地图",
    "url": "https://www.dytt8.com/plus/sitemap.html"
  }
]