{
  "cover_image": "https://img9.doubanio.com/view/photo/l_ratio_poster/public/p2918358085.jpg",
  "translated_name": null,
  "original_name": "谍徒迷局",
  "year": 2025,
  "country": "中国大陆",
  "genre": [
    "悬疑",
    "武侠",
    "古装"
  ],
  "language": "普通话",
  "subtitle": "中文",
  "release_date": "2025-02-14(中国大陆)",
  "imdb_rating": null,
  "douban_rating": null,
  "duration": "87分钟",
  "director": "王鹰 Ying Wang",
  "screenwriter": null,
  "actors": [
    "王珞嘉 Luojia Wang",
    "王九胜 Jiusheng Wang",
    "黎真安 Zhenan Li",
    "张春仲 Chunzhong Zhang",
    "石兆琪 Zhaoqi Shi"
  ],
  "synopsis": "宋·皇祐三年,涿郡府泗水县,因人口大量走失而引起民怨发生叛乱,县令宗朝虽将叛乱镇压,但走失的人口始终无法找回。刑部卧底遒辛治受太尉陆判官之命,顶替被暗杀的周广泗水帮帮主,通过卧底身份帮派搜集情报,从而调查人口走失案。遒辛治凭借酷似周广的外貌混入泗水帮,始终感觉杀机四伏。果不其然,遒辛治刚着手调查就遭遇暗杀,于是,卧底遒辛治与总铺头霄离渊一明一暗联手查案。但因案件错踪复杂,而遒辛治天马行空,乱拳打死老师傅似的破案方案,令霄离渊头痛不已。历经冲冲危险,最终案件终于得以侦破,遒辛治却放弃恢复身份,选择继续卧底生涯,踏上侦破新案件的征途。",
  "awards": null,
  "download_links": [
    {
      "type": "磁力链接",
      "link": "magnet:?xt=urn:btih:efac44931103d946e519347b9f06e27e6b9dc2b7&dn=%E9%98%B3%E5%85%89%E7%94%B5%E5%BD%B1dygod.org.%E8%b0%8D%E5%BE%92%E8%BF%B7%E5%8C%BA.2025.HD.1080P.%E5%9B%BD%E8%AF%AD%E4%B8%AD%E5%AD%97.mkv&tr=udp%3a%2f%2ftracker.opentrackr.org%3a1337%2fannounce&tr=udp%3a%2f%2fexodus.desync.com%3a6969%2fannounce"
    },
    {
      "type": "播放软件下载",
      "link": "https://dygod.org/js/player.htm"
    },
    {
      "type": "电影下载地址2",
      "link": "https://dygod.org/"
    }
  ],
  "source_file": "谍徒迷局.md"
}